streamz_pulsar/__init__.py
streamz_pulsar/base.py
streamz_pulsar/sinks.py
streamz_pulsar/sources/__init__.py
streamz_pulsar/sources/from_pulsar.py
streamz_pulsar-0.1.1.dist-info/METADATA
streamz_pulsar-0.1.1.dist-info/WHEEL
streamz_pulsar-0.1.1.dist-info/entry_points.txt
streamz_pulsar-0.1.1.dist-info/RECORD
